porringer_pip-0.1.1.dev3.dist-info/METADATA
porringer_pip-0.1.1.dev3.dist-info/WHEEL
porringer_pip-0.1.1.dev3.dist-info/entry_points.txt
porringer_pip-0.1.1.dev3.dist-info/licenses/LICENSE.md
porringer_pip/__init__.py
porringer_pip/plugin.py
porringer_pip/py.typed
porringer_pip-0.1.1.dev3.dist-info/RECORD
