Metadata-Version: 2.1
Name: porringer-pip
Version: 0.1.1.dev3
Home-page: https://github.com/Synodic-Software/Porringer-Pip
Author-Email: Synodic Software <contact@synodic.software>
License: MIT
Project-URL: Homepage, https://github.com/Synodic-Software/Porringer-Pip
Project-URL: Repository, https://github.com/Synodic-Software/Porringer-Pip
Requires-Python: >=3.11
Requires-Dist: porringer-core>=0.0.0
